warmup4ie/__init__.py
warmup4ie/warmup4ie.py
warmup4ie-0.1.5.dist-info/LICENSE
warmup4ie-0.1.5.dist-info/METADATA
warmup4ie-0.1.5.dist-info/WHEEL
warmup4ie-0.1.5.dist-info/top_level.txt
warmup4ie-0.1.5.dist-info/RECORD
