Metadata-Version: 2.1
Name: warmup4ie
Version: 0.1.5
Summary: client library for 4IE thermostat sold by warmup
Home-page: https://github.com/alex-0103/warmup4IE
Author: Alexander Hinz
Author-email: alex.hinz@plan-b-software.de
License: Apache
Platform: UNKNOWN
Classifier: Intended Audience :: Developers
Classifier: License :: OSI Approved :: Apache Software License 
Classifier: Programming Language :: Python
Classifier: Programming Language :: Python :: 2
Classifier: Programming Language :: Python :: 3
Classifier: Operating System :: OS Independent
Classifier: Topic :: Home Automation
Classifier: Topic :: Software Development :: Libraries
